distmap/__init__.py
distmap/_l1.py
distmap/_l2.py
distmap/_version.py
distmap/backend.py
distmap/jit_utils.py
distmap/jitfields.py
distmap/l1.py
distmap/l2.py
distmap/utils.py
torch_distmap-0.2.0.dist-info/LICENSE
torch_distmap-0.2.0.dist-info/METADATA
torch_distmap-0.2.0.dist-info/WHEEL
torch_distmap-0.2.0.dist-info/top_level.txt
torch_distmap-0.2.0.dist-info/RECORD
